bcsl/__init__.py
bcsl/aee.py
bcsl/bcsl.py
bcsl/fci.py
bcsl/graph_utils.py
bcsl/hill_climber.py
bcsl/hiton.py
bcsl/scores/__init__.py
bcsl/scores/bdeu.py
bcsl/scores/gaussian_bic.py
examples/__init__.py
examples/easy.py
examples/hard.py
examples/utilities.py
bcsl_python-0.8.0.dist-info/LICENSE.md
bcsl_python-0.8.0.dist-info/METADATA
bcsl_python-0.8.0.dist-info/WHEEL
bcsl_python-0.8.0.dist-info/top_level.txt
bcsl_python-0.8.0.dist-info/RECORD
