Metadata-Version: 2.1
Name: bcsl-python
Version: 0.8.0
Summary: Bootstrap-based Causal Structure Learning
Home-page: https://github.com/albertbuchard/bcsl_python
Author: Guo, Xianjie
Author-email: albert.buchard@gmail.com
Classifier: Programming Language :: Python :: 3
Classifier: License :: OSI Approved :: MIT License
Classifier: Operating System :: OS Independent
Requires-Python: >=3.6
License-File: LICENSE.md
Requires-Dist: numpy (>=1.18.0)
Requires-Dist: scipy (>=1.4.0)
Requires-Dist: scikit-learn (>=0.22.0)
Requires-Dist: causal-learn (==0.1.3.8)
